sequelize_to_excel
