Metadata-Version: 1.2
Name: sequelize-to-excel
Version: 1.0.9
Summary: map your sequelize columns to excel
Home-page: https://github.com/darshan99/sequelize_to_excel
Author: Darshan Bharat
Author-email: mailshahdarshan@gmail.com
License: UNKNOWN
Keywords: Node,excel,Sequelize
Platform: UNKNOWN
Classifier: Programming Language :: Python :: 3
Classifier: License :: OSI Approved :: MIT License
Classifier: Operating System :: OS Independent
Requires-Python: >=3.6
